{
  "_class": "bitmap",
  "booleanOperation": 0,
  "clippingMask": "{{0, 0}, {1, 1}}",
  "do_objectID": "9F5983C0-1BB9-4D65-A30D-2D49383AD95F",
  "exportOptions": {
    "_class": "exportOptions",
    "do_objectID": "8F3C4053-824D-4C9C-BDA5-B51C14A0A28B",
    "exportFormats": [
    ],
    "includedLayerIds": [
    ],
    "layerOptions": 0,
    "shouldTrim": false
  },
  "fillReplacesImage": false,
  "frame": {
    "_class": "rect",
    "constrainProportions": true,
    "do_objectID": "D38C995B-24D9-4C83-8190-8B58AA8613D5",
    "height": 173,
    "width": 259,
    "x": 742,
    "y": 473
  },
  "image": {
    "_class": "MSJSONFileReference",
    "_ref": "images/b7e3433d64bdb3641d0f3569c639ad2afb807ae9.png",
    "_ref_class": "MSImageData"
  },
  "intendedDPI": 72,
  "isFixedToViewport": false,
  "isFlippedHorizontal": false,
  "isFlippedVertical": false,
  "isLocked": false,
  "isVisible": true,
  "layerListExpandedType": 0,
  "name": "Bitmap Copy 2",
  "nameIsFixed": false,
  "resizingConstraint": 63,
  "resizingType": 0,
  "rotation": 0,
  "shouldBreakMaskChain": false,
  "style": {
    "_class": "style",
    "do_objectID": "11533971-CE7A-410A-B887-42C2D329F2EF",
    "endMarkerType": 0,
    "miterLimit": 10,
    "startMarkerType": 0,
    "windingRule": 1
  },
  "userInfo": {
    "com.animaapp.stc-sketch-plugin": {
      "kModelPropertiesKey": {
      }
    }
  }
}